uneff/__init__.py
uneff/core.py
uneff/uneff_mappings.csv
uneff-1.0.1.dist-info/licenses/LICENSE
uneff-1.0.1.dist-info/METADATA
uneff-1.0.1.dist-info/WHEEL
uneff-1.0.1.dist-info/entry_points.txt
uneff-1.0.1.dist-info/top_level.txt
uneff-1.0.1.dist-info/RECORD
