Metadata-Version: 2.4
Name: uneff
Version: 1.0.1
Summary: Remove BOM and problematic Unicode characters from text files
Home-page: https://github.com/mkiiim/uneff
Author: Mark
Author-email: Mark <mark.emila@gmail.com>
Maintainer-email: Mark <mark.emila@gmail.com>
License: MIT
Project-URL: Homepage, https://github.com/mkiiim/uneff
Project-URL: Documentation, https://github.com/mkiiim/uneff#readme
Project-URL: Repository, https://github.com/mkiiim/uneff.git
Project-URL: Bug Reports, https://github.com/mkiiim/uneff/issues
Keywords: unicode,bom,text-processing,csv-cleaning,data-cleaning,file-processing
Classifier: Development Status :: 5 - Production/Stable
Classifier: Intended Audience :: Developers
Classifier: Intended Audience :: System Administrators
Classifier: Topic :: Text Processing :: Filters
Classifier: Topic :: Utilities
Classifier: Topic :: Software Development :: Libraries :: Python Modules
Classifier: License :: OSI Approved :: MIT License
Classifier: Programming Language :: Python :: 3
Classifier: Programming Language :: Python :: 3.7
Classifier: Programming Language :: Python :: 3.8
Classifier: Programming Language :: Python :: 3.9
Classifier: Programming Language :: Python :: 3.10
Classifier: Programming Language :: Python :: 3.11
Classifier: Programming Language :: Python :: 3.12
Classifier: Operating System :: OS Independent
Requires-Python: >=3.7
License-File: LICENSE
Dynamic: author
Dynamic: home-page
Dynamic: license-file
Dynamic: requires-python
